CHANGELOG
LICENSE
MANIFEST.in
README.md
setup.py
scripts/td
td/__init__.py
td/logger.py
td/main.py
td/model.py
td.egg-info/PKG-INFO
td.egg-info/SOURCES.txt
td.egg-info/dependency_links.txt
td.egg-info/top_level.txt