Metadata-Version: 1.1
Name: td
Version: 0.3
Summary: A non-offensive, per project ToDo manager.
Home-page: http://github.com/KenjiTakahashi/td
Author: Karol "Kenji Takahashi" Woźniak
Author-email: wozniakk@gmail.com
License: GPL3
Platform: UNKNOWN
Classifier: Development Status :: 4 - Beta
Classifier: Environment :: Console
Classifier: Intended Audience :: Developers
Classifier: Intended Audience :: End Users/Desktop
Classifier: License :: OSI Approved :: GNU General Public License v3 or later (GPLv3+)
Classifier: Natural Language :: English
Classifier: Operating System :: OS Independent
Classifier: Programming Language :: Python :: 3
Classifier: Topic :: Utilities
